{"name":"思","slug":"思","count":2,"postlist":[{"title":"思2","uid":"3ae0255690cd832e2512af93d9675cc2","slug":"思2","date":"2022-04-16T03:31:23.000Z","updated":"2022-07-30T09:22:24.000Z","comments":true,"path":"api/articles/思2.json","keywords":null,"cover":"https://homo1145141919810.oss-cn-shanghai.aliyuncs.com/img/91.jpg","text":"11国家是怎么产生的？国家产生于人。人为什么要建立国家呢？让自己变得强大，不收剥夺或者残害他人，国家是人私心的产物。那要是世界上的人都没有私心，那就迎来了和平。或者说：和平的到来要等到最后一个爱国者的死亡。不知什么时候。 12人要是能对自己的话过一遍脑子，世界也不会如此无理，可惜...","link":"","photos":[],"count_time":{"symbolsCount":555,"symbolsTime":"1 mins."},"categories":[{"name":"认真哲思","slug":"认真哲思","count":4,"path":"api/categories/认真哲思.json"}],"tags":[{"name":"思","slug":"思","count":2,"path":"api/tags/思.json"}],"author":{"name":"艾伦·耶格尔","slug":"blog-author","avatar":"https://homo1145141919810.oss-cn-shanghai.aliyuncs.com/img/79.jpg","link":"/","description":"一个程序猿","socials":{"github":"","twitter":"","stackoverflow":"","wechat":"","qq":"","weibo":"","zhihu":"","csdn":"","juejin":"","customs":{"bilibili":{"icon":"iconfont icon-icon_bilibili-square","link":"https://space.bilibili.com/1179276505?spm_id_from=333.337.0.0"}}}}},{"title":"思1","uid":"302c1956f6968bb90962b7223d6e801a","slug":"思1","date":"2022-04-16T03:22:22.000Z","updated":"2022-07-30T09:22:24.000Z","comments":true,"path":"api/articles/思1.json","keywords":null,"cover":"https://homo1145141919810.oss-cn-shanghai.aliyuncs.com/img/90.jpg","text":"1.爱情若能被复刻，那只是昂贵的商品罢了，我并不渴望；所以我并不想拥有和别人一样的爱情，因为我知道，真正的爱情是无法被复刻的。 2.不必渴望成为他人，每个人都有自己的活法。 3.读无营养的书，就是在娱乐化的生活中以为自己在学习。 4.我越思考，越接近真理，却越发现改变现实的无能为...","link":"","photos":[],"count_time":{"symbolsCount":390,"symbolsTime":"1 mins."},"categories":[{"name":"认真哲思","slug":"认真哲思","count":4,"path":"api/categories/认真哲思.json"}],"tags":[{"name":"思","slug":"思","count":2,"path":"api/tags/思.json"}],"author":{"name":"艾伦·耶格尔","slug":"blog-author","avatar":"https://homo1145141919810.oss-cn-shanghai.aliyuncs.com/img/79.jpg","link":"/","description":"一个程序猿","socials":{"github":"","twitter":"","stackoverflow":"","wechat":"","qq":"","weibo":"","zhihu":"","csdn":"","juejin":"","customs":{"bilibili":{"icon":"iconfont icon-icon_bilibili-square","link":"https://space.bilibili.com/1179276505?spm_id_from=333.337.0.0"}}}}}]}